<?xml version="1.0" encoding="utf-8" standalone="yes"?>
<imgdir name="9800017.img">
    <imgdir name="info">
        <int name="hideName" value="1" />
        <int name="dcTop" value="-117" />
        <int name="dcBottom" value="0" />
        <int name="dcLeft" value="-45" />
        <int name="dcRight" value="45" />
    </imgdir>
    <imgdir name="stand">
        <canvas name="0" width="92" height="119">
            <vector name="origin" x="45" y="117" />
        </canvas>
        <canvas name="1" width="94" height="118">
            <vector name="origin" x="47" y="116" />
        </canvas>
        <canvas name="2" width="95" height="118">
            <vector name="origin" x="47" y="116" />
        </canvas>
        <canvas name="3" width="92" height="118">
            <vector name="origin" x="44" y="116" />
        </canvas>
        <canvas name="4" width="104" height="118">
            <vector name="origin" x="44" y="115" />
        </canvas>
        <canvas name="5" width="109" height="120">
            <vector name="origin" x="44" y="117" />
        </canvas>
        <canvas name="6" width="127" height="121">
            <vector name="origin" x="61" y="118" />
        </canvas>
        <canvas name="7" width="127" height="122">
            <vector name="origin" x="62" y="119" />
        </canvas>
        <canvas name="8" width="123" height="121">
            <vector name="origin" x="61" y="118" />
        </canvas>
        <canvas name="9" width="112" height="120">
            <vector name="origin" x="55" y="117" />
        </canvas>
        <canvas name="10" width="100" height="120">
            <vector name="origin" x="50" y="117" />
        </canvas>
        <canvas name="11" width="89" height="117">
            <vector name="origin" x="44" y="115" />
        </canvas>
        <canvas name="12" width="89" height="118">
            <vector name="origin" x="44" y="116" />
        </canvas>
        <canvas name="13" width="91" height="118">
            <vector name="origin" x="44" y="116" />
        </canvas>
    </imgdir>
</imgdir>