<?xml version="1.0" encoding="utf-8" standalone="yes"?>
<imgdir name="MonsterBook.img">
    <imgdir name="100100">
        <string name="episode" value="" />
        <imgdir name="map">
            <int name="0" value="910000001" />
        </imgdir>
        <imgdir name="reward">
            <int name="0" value="1092003" />
            <int name="1" value="2000000" />
            <int name="2" value="2000003" />
        </imgdir>
    </imgdir>
    <imgdir name="100101">
        <string name="episode" value="" />
        <imgdir name="map">
            <int name="0" value="104040000" />
        </imgdir>
        <imgdir name="reward">
            <int name="0" value="1040010" />
            <int name="1" value="1061008" />
            <int name="2" value="1092003" />
            <int name="3" value="2000000" />
            <int name="4" value="2000003" />
        </imgdir>
    </imgdir>
    <imgdir name="120100">
        <string name="episode" value="" />
        <imgdir name="map">
            <int name="0" value="104040000" />
        </imgdir>
        <imgdir name="reward">
            <int name="0" value="1040002" />
            <int name="1" value="1060002" />
            <int name="2" value="1061002" />
            <int name="3" value="2000000" />
            <int name="4" value="2000003" />
        </imgdir>
    </imgdir>
    <imgdir name="130100">
        <string name="episode" value="" />
        <imgdir name="map">
            <int name="0" value="104040000" />
        </imgdir>
        <imgdir name="reward">
            <int name="0" value="1041006" />
            <int name="1" value="1060006" />
            <int name="2" value="1082002" />
            <int name="3" value="2000000" />
            <int name="4" value="2000003" />
        </imgdir>
    </imgdir>
    <imgdir name="130101">
        <string name="episode" value="" />
        <imgdir name="map">
            <int name="0" value="104040000" />
        </imgdir>
        <imgdir name="reward">
            <int name="0" value="1041011" />
            <int name="1" value="1082002" />
            <int name="2" value="1302024" />
            <int name="3" value="2000000" />
            <int name="4" value="2000003" />
        </imgdir>
    </imgdir>
    <imgdir name="1110100">
        <string name="episode" value="" />
        <imgdir name="map">
            <int name="0" value="100020000" />
        </imgdir>
        <imgdir name="reward">
            <int name="0" value="1002019" />
            <int name="1" value="1002080" />
            <int name="2" value="1002082" />
            <int name="3" value="1002083" />
            <int name="4" value="1002395" />
            <int name="5" value="1302005" />
            <int name="6" value="1332002" />
            <int name="7" value="1382003" />
            <int name="8" value="1432001" />
            <int name="9" value="1442039" />
            <int name="10" value="1452003" />
            <int name="11" value="1472001" />
            <int name="12" value="1482001" />
            <int name="13" value="1492001" />
            <int name="14" value="2000001" />
            <int name="15" value="2002031" />
        </imgdir>
    </imgdir>
    <imgdir name="2220100">
        <string name="episode" value="" />
        <imgdir name="map">
            <int name="0" value="100020100" />
        </imgdir>
        <imgdir name="reward">
            <int name="0" value="1002019" />
            <int name="1" value="1002080" />
            <int name="2" value="1002082" />
            <int name="3" value="1002083" />
            <int name="4" value="1002395" />
            <int name="5" value="1302005" />
            <int name="6" value="1332002" />
            <int name="7" value="1382003" />
            <int name="8" value="1432001" />
            <int name="9" value="1442039" />
            <int name="10" value="1452003" />
            <int name="11" value="1472001" />
            <int name="12" value="1482001" />
            <int name="13" value="1492001" />
            <int name="14" value="2000001" />
            <int name="15" value="2002031" />
        </imgdir>
    </imgdir>
    <imgdir name="1130100">
        <string name="episode" value="" />
        <imgdir name="map">
            <int name="0" value="100020000" />
        </imgdir>
        <imgdir name="reward">
            <int name="0" value="1002080" />
            <int name="1" value="1002082" />
            <int name="2" value="1002083" />
            <int name="3" value="1002395" />
            <int name="4" value="1032000" />
            <int name="5" value="1032001" />
            <int name="6" value="1032003" />
            <int name="7" value="1032009" />
            <int name="8" value="1302005" />
            <int name="9" value="1332002" />
            <int name="10" value="1382003" />
            <int name="11" value="1432001" />
            <int name="12" value="1442039" />
            <int name="13" value="1452003" />
            <int name="14" value="1472001" />
            <int name="15" value="1482001" />
            <int name="16" value="1492001" />
            <int name="17" value="2000001" />
            <int name="18" value="2002031" />
            <int name="19" value="4000019" />
        </imgdir>
    </imgdir>
    <imgdir name="1140130">
        <string name="episode" value="" />
        <imgdir name="map">
            <int name="0" value="100020100" />
        </imgdir>
        <imgdir name="reward">
            <int name="0" value="1002080" />
            <int name="1" value="1002082" />
            <int name="2" value="1002083" />
            <int name="3" value="1002395" />
            <int name="4" value="1032000" />
            <int name="5" value="1032001" />
            <int name="6" value="1032003" />
            <int name="7" value="1032009" />
            <int name="8" value="1302005" />
            <int name="9" value="1332002" />
            <int name="10" value="1382003" />
            <int name="11" value="1432001" />
            <int name="12" value="1442039" />
            <int name="13" value="1452003" />
            <int name="14" value="1472001" />
            <int name="15" value="1482001" />
            <int name="16" value="1492001" />
            <int name="17" value="2000001" />
            <int name="18" value="2002031" />
            <int name="19" value="4000019" />
        </imgdir>
    </imgdir>
    <imgdir name="9420502">
        <string name="episode" value="" />
        <imgdir name="map">
            <int name="0" value="103000007" />
        </imgdir>
        <imgdir name="reward">
            <int name="0" value="1032000" />
            <int name="1" value="1032001" />
            <int name="2" value="1032003" />
            <int name="3" value="1032009" />
            <int name="4" value="1072004" />
            <int name="5" value="1072042" />
            <int name="6" value="1072043" />
            <int name="7" value="1302005" />
            <int name="8" value="1332002" />
            <int name="9" value="1382003" />
            <int name="10" value="1432001" />
            <int name="11" value="1442039" />
            <int name="12" value="1452003" />
            <int name="13" value="1472001" />
            <int name="14" value="1482001" />
            <int name="15" value="1492001" />
            <int name="16" value="2000001" />
            <int name="17" value="2002031" />
            <int name="18" value="4000366" />
        </imgdir>
    </imgdir>
    <imgdir name="210100">
        <string name="episode" value="" />
        <imgdir name="map">
            <int name="0" value="103000101" />
        </imgdir>
        <imgdir name="reward">
            <int name="0" value="1082148" />
            <int name="1" value="1082150" />
            <int name="2" value="1112921" />
            <int name="3" value="1452001" />
            <int name="4" value="1492003" />
            <int name="5" value="2000002" />
            <int name="6" value="2000006" />
            <int name="7" value="4000004" />
            <int name="8" value="4031089" />
        </imgdir>
    </imgdir>
    <imgdir name="9400538">
        <string name="episode" value="" />
        <imgdir name="map">
            <int name="0" value="103000101" />
        </imgdir>
        <imgdir name="reward">
            <int name="0" value="1082145" />
            <int name="1" value="1082150" />
            <int name="2" value="1112921" />
            <int name="3" value="1332013" />
            <int name="4" value="1432008" />
            <int name="5" value="2000002" />
            <int name="6" value="2000006" />
            <int name="7" value="4007010" />
            <int name="8" value="4031089" />
        </imgdir>
    </imgdir>
    <imgdir name="1210103">
        <string name="episode" value="" />
        <imgdir name="map">
            <int name="0" value="103000101" />
        </imgdir>
        <imgdir name="reward">
            <int name="0" value="1082147" />
            <int name="1" value="1082150" />
            <int name="2" value="1112921" />
            <int name="3" value="1372004" />
            <int name="4" value="1472006" />
            <int name="5" value="2000002" />
            <int name="6" value="2000006" />
            <int name="7" value="4007008" />
            <int name="8" value="4031089" />
        </imgdir>
    </imgdir>
    <imgdir name="7120103">
        <string name="episode" value="" />
        <imgdir name="map">
            <int name="0" value="103000101" />
        </imgdir>
        <imgdir name="reward">
            <int name="0" value="1082146" />
            <int name="1" value="1082150" />
            <int name="2" value="1112921" />
            <int name="3" value="1302006" />
            <int name="4" value="1442014" />
            <int name="5" value="1482002" />
            <int name="6" value="2000002" />
            <int name="7" value="2000006" />
            <int name="8" value="4007009" />
            <int name="9" value="4031089" />
        </imgdir>
    </imgdir>
    <imgdir name="2100102">
        <string name="episode" value="" />
        <imgdir name="map">
            <int name="0" value="260010000" />
        </imgdir>
        <imgdir name="reward">
            <int name="0" value="1002026" />
            <int name="1" value="1002089" />
            <int name="2" value="1004001" />
            <int name="3" value="1102082" />
            <int name="4" value="1102083" />
            <int name="5" value="2000002" />
            <int name="6" value="2000006" />
            <int name="7" value="4000330" />
            <int name="8" value="4007017" />
        </imgdir>
    </imgdir>
    <imgdir name="2110300">
        <string name="episode" value="" />
        <imgdir name="map">
            <int name="0" value="260010200" />
        </imgdir>
        <imgdir name="reward">
            <int name="0" value="1002089" />
            <int name="1" value="1002090" />
            <int name="2" value="1092008" />
            <int name="3" value="1102079" />
            <int name="4" value="1102081" />
            <int name="5" value="2000002" />
            <int name="6" value="2000006" />
            <int name="7" value="4000350" />
            <int name="8" value="4007017" />
        </imgdir>
    </imgdir>
    <imgdir name="2230110">
        <string name="episode" value="" />
        <imgdir name="map">
            <int name="0" value="260010200" />
        </imgdir>
        <imgdir name="reward">
            <int name="0" value="1002090" />
            <int name="1" value="1004000" />
            <int name="2" value="1004001" />
            <int name="3" value="1102079" />
            <int name="4" value="1102080" />
            <int name="5" value="1102083" />
            <int name="6" value="2000002" />
            <int name="7" value="2000006" />
            <int name="8" value="4000018" />
            <int name="9" value="4007017" />
        </imgdir>
    </imgdir>
    <imgdir name="2230111">
        <string name="episode" value="" />
        <imgdir name="map">
            <int name="0" value="101030402" />
        </imgdir>
        <imgdir name="reward">
            <int name="0" value="1002026" />
            <int name="1" value="1004000" />
            <int name="2" value="1092008" />
            <int name="3" value="1102080" />
            <int name="4" value="1102081" />
            <int name="5" value="1102082" />
            <int name="6" value="2000002" />
            <int name="7" value="2000006" />
            <int name="8" value="4000197" />
            <int name="9" value="4007017" />
        </imgdir>
    </imgdir>
    <imgdir name="2230102">
        <string name="episode" value="" />
        <imgdir name="map">
            <int name="0" value="101030100" />
        </imgdir>
        <imgdir name="reward">
            <int name="0" value="1072012" />
            <int name="1" value="1073000" />
            <int name="2" value="1302002" />
            <int name="3" value="1322012" />
            <int name="4" value="1382054" />
            <int name="5" value="1442065" />
            <int name="6" value="1462000" />
            <int name="7" value="2020005" />
            <int name="8" value="2022000" />
            <int name="9" value="4000021" />
            <int name="10" value="4007017" />
        </imgdir>
    </imgdir>
    <imgdir name="2110301">
        <string name="episode" value="" />
        <imgdir name="map">
            <int name="0" value="260010300" />
        </imgdir>
        <imgdir name="reward">
            <int name="0" value="1072054" />
            <int name="1" value="1072055" />
            <int name="2" value="1322012" />
            <int name="3" value="1382054" />
            <int name="4" value="1402008" />
            <int name="5" value="1432013" />
            <int name="6" value="1452054" />
            <int name="7" value="2020005" />
            <int name="8" value="2022000" />
            <int name="9" value="4007011" />
            <int name="10" value="4007017" />
        </imgdir>
    </imgdir>
    <imgdir name="2100105">
        <string name="episode" value="" />
        <imgdir name="map">
            <int name="0" value="260010300" />
        </imgdir>
        <imgdir name="reward">
            <int name="0" value="1072012" />
            <int name="1" value="1072054" />
            <int name="2" value="1422001" />
            <int name="3" value="1462000" />
            <int name="4" value="1472007" />
            <int name="5" value="1482004" />
            <int name="6" value="1492004" />
            <int name="7" value="2020005" />
            <int name="8" value="2022000" />
            <int name="9" value="4007011" />
            <int name="10" value="4007017" />
        </imgdir>
    </imgdir>
    <imgdir name="2100103">
        <string name="episode" value="" />
        <imgdir name="map">
            <int name="0" value="260010700" />
        </imgdir>
        <imgdir name="reward">
            <int name="0" value="1050018" />
            <int name="1" value="1072055" />
            <int name="2" value="1072056" />
            <int name="3" value="1332012" />
            <int name="4" value="1402008" />
            <int name="5" value="1422001" />
            <int name="6" value="1432013" />
            <int name="7" value="1472007" />
            <int name="8" value="1492004" />
            <int name="9" value="2020005" />
            <int name="10" value="2022000" />
            <int name="11" value="4007013" />
            <int name="12" value="4007017" />
        </imgdir>
    </imgdir>
    <imgdir name="2100108">
        <string name="episode" value="" />
        <imgdir name="map">
            <int name="0" value="260010700" />
        </imgdir>
        <imgdir name="reward">
            <int name="0" value="1051017" />
            <int name="1" value="1072056" />
            <int name="2" value="1073000" />
            <int name="3" value="1302002" />
            <int name="4" value="1332012" />
            <int name="5" value="1442065" />
            <int name="6" value="1452054" />
            <int name="7" value="1482004" />
            <int name="8" value="2020005" />
            <int name="9" value="2022000" />
            <int name="10" value="4007013" />
            <int name="11" value="4007017" />
        </imgdir>
    </imgdir>
    <imgdir name="3210100">
        <string name="episode" value="" />
        <imgdir name="map">
            <int name="0" value="260010400" />
        </imgdir>
        <imgdir name="reward">
            <int name="0" value="1050018" />
            <int name="1" value="1051017" />
            <int name="2" value="2020005" />
            <int name="3" value="2022000" />
            <int name="4" value="4000021" />
            <int name="5" value="4001006" />
            <int name="6" value="4007017" />
        </imgdir>
    </imgdir>
    <imgdir name="3220000">
        <string name="episode" value="" />
        <imgdir name="map">
            <int name="0" value="100020100" />
        </imgdir>
        <imgdir name="reward">
            <int name="0" value="1002019" />
            <int name="1" value="1002080" />
            <int name="2" value="1002082" />
            <int name="3" value="1002083" />
            <int name="4" value="1002395" />
            <int name="5" value="1032000" />
            <int name="6" value="1032001" />
            <int name="7" value="1032003" />
            <int name="8" value="1032009" />
            <int name="9" value="1072004" />
            <int name="10" value="1072042" />
            <int name="11" value="1072043" />
            <int name="12" value="1082145" />
            <int name="13" value="1082146" />
            <int name="14" value="1082147" />
            <int name="15" value="1082148" />
            <int name="16" value="1082150" />
            <int name="17" value="1112921" />
            <int name="18" value="2070001" />
            <int name="19" value="2330001" />
        </imgdir>
    </imgdir>
    <imgdir name="3220001">
        <string name="episode" value="" />
        <imgdir name="map">
            <int name="0" value="260010001" />
        </imgdir>
        <imgdir name="reward">
            <int name="0" value="1002026" />
            <int name="1" value="1002089" />
            <int name="2" value="1002090" />
            <int name="3" value="1004000" />
            <int name="4" value="1004001" />
            <int name="5" value="1072012" />
            <int name="6" value="1072054" />
            <int name="7" value="1072055" />
            <int name="8" value="1072056" />
            <int name="9" value="1073000" />
            <int name="10" value="1092008" />
            <int name="11" value="1102079" />
            <int name="12" value="1102080" />
            <int name="13" value="1102081" />
            <int name="14" value="1102082" />
            <int name="15" value="1102083" />
            <int name="16" value="2060001" />
            <int name="17" value="2061001" />
            <int name="18" value="2070009" />
            <int name="19" value="2330002" />
        </imgdir>
    </imgdir>
    <imgdir name="2220000">
        <string name="episode" value="" />
        <imgdir name="map">
            <int name="0" value="104040000" />
        </imgdir>
        <imgdir name="reward">
            <int name="0" value="1040002" />
            <int name="1" value="1040010" />
            <int name="2" value="1041006" />
            <int name="3" value="1041011" />
            <int name="4" value="1060002" />
            <int name="5" value="1060006" />
            <int name="6" value="1061002" />
            <int name="7" value="1061008" />
            <int name="8" value="1082002" />
            <int name="9" value="1092003" />
        </imgdir>
    </imgdir>
    <imgdir name="3110100">
        <string name="episode" value="" />
        <imgdir name="map">
            <int name="0" value="107000000" />
        </imgdir>
        <imgdir name="reward">
            <int name="0" value="1082148" />
            <int name="1" value="1082150" />
            <int name="2" value="1112921" />
            <int name="3" value="1452001" />
            <int name="4" value="1492003" />
            <int name="5" value="2000002" />
            <int name="6" value="2000006" />
            <int name="7" value="4000032" />
            <int name="8" value="4031666" />
        </imgdir>
    </imgdir>
    <imgdir name="9800002">
        <string name="episode" value="" />
        <imgdir name="map">
            <int name="0" value="107000000" />
        </imgdir>
        <imgdir name="reward">
            <int name="0" value="1082145" />
            <int name="1" value="1082150" />
            <int name="2" value="1112921" />
            <int name="3" value="1332013" />
            <int name="4" value="1432008" />
            <int name="5" value="2000002" />
            <int name="6" value="2000006" />
            <int name="7" value="4007020" />
            <int name="8" value="4031666" />
        </imgdir>
    </imgdir>
    <imgdir name="9800001">
        <string name="episode" value="" />
        <imgdir name="map">
            <int name="0" value="107000000" />
        </imgdir>
        <imgdir name="reward">
            <int name="0" value="1082146" />
            <int name="1" value="1082150" />
            <int name="2" value="1112921" />
            <int name="3" value="1302006" />
            <int name="4" value="1442014" />
            <int name="5" value="1482002" />
            <int name="6" value="2000002" />
            <int name="7" value="2000006" />
            <int name="8" value="4007019" />
            <int name="9" value="4031666" />
        </imgdir>
    </imgdir>
    <imgdir name="9800000">
        <string name="episode" value="" />
        <imgdir name="map">
            <int name="0" value="107000000" />
        </imgdir>
        <imgdir name="reward">
            <int name="0" value="1082147" />
            <int name="1" value="1082150" />
            <int name="2" value="1112921" />
            <int name="3" value="1372004" />
            <int name="4" value="1472006" />
            <int name="5" value="2000002" />
            <int name="6" value="2000006" />
            <int name="7" value="4007018" />
            <int name="8" value="4031666" />
        </imgdir>
    </imgdir>
    <imgdir name="6220000">
        <string name="episode" value="" />
        <imgdir name="map">
            <int name="0" value="107000000" />
        </imgdir>
        <imgdir name="reward">
            <int name="0" value="1082145" />
            <int name="1" value="1082146" />
            <int name="2" value="1082147" />
            <int name="3" value="1082148" />
            <int name="4" value="1302006" />
            <int name="5" value="1332013" />
            <int name="6" value="1372004" />
            <int name="7" value="1432008" />
            <int name="8" value="1442014" />
            <int name="9" value="1452001" />
            <int name="10" value="1472006" />
            <int name="11" value="1482002" />
            <int name="12" value="1492003" />
            <int name="13" value="2070001" />
            <int name="14" value="2330001" />
            <int name="15" value="4007016" />
        </imgdir>
    </imgdir>
    <imgdir name="2110200">
        <string name="episode" value="" />
        <imgdir name="map">
            <int name="0" value="106010100" />
        </imgdir>
        <imgdir name="reward">
            <int name="0" value="1002002" />
            <int name="1" value="1040004" />
            <int name="2" value="1060023" />
            <int name="3" value="1072015" />
            <int name="4" value="1082180" />
            <int name="5" value="1112408" />
            <int name="6" value="1322008" />
            <int name="7" value="1332020" />
            <int name="8" value="2020005" />
            <int name="9" value="2022000" />
            <int name="10" value="4010000" />
            <int name="11" value="4020000" />
            <int name="12" value="4021017" />
        </imgdir>
    </imgdir>
    <imgdir name="3000001">
        <string name="episode" value="" />
        <imgdir name="map">
            <int name="0" value="106010100" />
        </imgdir>
        <imgdir name="reward">
            <int name="0" value="1002010" />
            <int name="1" value="1040015" />
            <int name="2" value="1060022" />
            <int name="3" value="1072285" />
            <int name="4" value="1082019" />
            <int name="5" value="1112407" />
            <int name="6" value="1372001" />
            <int name="7" value="1402006" />
            <int name="8" value="2020005" />
            <int name="9" value="2022000" />
            <int name="10" value="4003003" />
            <int name="11" value="4007011" />
            <int name="12" value="4010006" />
            <int name="13" value="4020006" />
        </imgdir>
    </imgdir>
    <imgdir name="3210800">
        <string name="episode" value="" />
        <imgdir name="map">
            <int name="0" value="106010100" />
        </imgdir>
        <imgdir name="reward">
            <int name="0" value="1002613" />
            <int name="1" value="1041064" />
            <int name="2" value="1061057" />
            <int name="3" value="1072044" />
            <int name="4" value="1082030" />
            <int name="5" value="1112931" />
            <int name="6" value="1432016" />
            <int name="7" value="1462005" />
            <int name="8" value="2020005" />
            <int name="9" value="2022000" />
            <int name="10" value="4000021" />
            <int name="11" value="4010001" />
            <int name="12" value="4020001" />
        </imgdir>
    </imgdir>
    <imgdir name="5200000">
        <string name="episode" value="" />
        <imgdir name="map">
            <int name="0" value="106010101" />
        </imgdir>
        <imgdir name="reward">
            <int name="0" value="1002125" />
            <int name="1" value="1040071" />
            <int name="2" value="1060012" />
            <int name="3" value="1072071" />
            <int name="4" value="1082003" />
            <int name="5" value="1322008" />
            <int name="6" value="1442050" />
            <int name="7" value="1452006" />
            <int name="8" value="2020005" />
            <int name="9" value="2022000" />
            <int name="10" value="4004000" />
            <int name="11" value="4010002" />
            <int name="12" value="4020004" />
        </imgdir>
    </imgdir>
    <imgdir name="3000000">
        <string name="episode" value="" />
        <imgdir name="map">
            <int name="0" value="106010102" />
        </imgdir>
        <imgdir name="reward">
            <int name="0" value="1002074" />
            <int name="1" value="1040032" />
            <int name="2" value="1060008" />
            <int name="3" value="1072044" />
            <int name="4" value="1082012" />
            <int name="5" value="1472013" />
            <int name="6" value="1482005" />
            <int name="7" value="2020005" />
            <int name="8" value="2022000" />
            <int name="9" value="4004002" />
            <int name="10" value="4010004" />
            <int name="11" value="4020003" />
        </imgdir>
    </imgdir>
    <imgdir name="5130101">
        <string name="episode" value="" />
        <imgdir name="map">
            <int name="0" value="106010102" />
        </imgdir>
        <imgdir name="reward">
            <int name="0" value="1002044" />
            <int name="1" value="1041061" />
            <int name="2" value="1061010" />
            <int name="3" value="1072009" />
            <int name="4" value="1082019" />
            <int name="5" value="1482005" />
            <int name="6" value="1492005" />
            <int name="7" value="2020005" />
            <int name="8" value="2022000" />
            <int name="9" value="4004001" />
            <int name="10" value="4010003" />
            <int name="11" value="4020007" />
        </imgdir>
    </imgdir>
    <imgdir name="5200001">
        <string name="episode" value="" />
        <imgdir name="map">
            <int name="0" value="106010102" />
            <int name="1" value="106010105" />
        </imgdir>
        <imgdir name="reward">
            <int name="0" value="1002610" />
            <int name="1" value="1032006" />
            <int name="2" value="1041017" />
            <int name="3" value="1062004" />
            <int name="4" value="1072071" />
            <int name="5" value="1082003" />
            <int name="6" value="1462005" />
            <int name="7" value="1472013" />
            <int name="8" value="2020005" />
            <int name="9" value="2022000" />
            <int name="10" value="4004003" />
            <int name="11" value="4007011" />
            <int name="12" value="4010005" />
            <int name="13" value="4020002" />
        </imgdir>
    </imgdir>
    <imgdir name="5200002">
        <string name="episode" value="" />
        <imgdir name="map">
            <int name="0" value="106010102" />
            <int name="1" value="106010106" />
        </imgdir>
        <imgdir name="reward">
            <int name="0" value="1002124" />
            <int name="1" value="1032004" />
            <int name="2" value="1061023" />
            <int name="3" value="1072015" />
            <int name="4" value="1082180" />
            <int name="5" value="1442050" />
            <int name="6" value="1452006" />
            <int name="7" value="2020005" />
            <int name="8" value="2022000" />
            <int name="9" value="4000021" />
            <int name="10" value="4004000" />
            <int name="11" value="4010001" />
            <int name="12" value="4020001" />
        </imgdir>
    </imgdir>
    <imgdir name="5150003">
        <string name="episode" value="" />
        <imgdir name="map">
            <int name="0" value="106010104" />
            <int name="1" value="106010106" />
        </imgdir>
        <imgdir name="reward">
            <int name="0" value="1002057" />
            <int name="1" value="1032005" />
            <int name="2" value="1052095" />
            <int name="3" value="1072285" />
            <int name="4" value="1082030" />
            <int name="5" value="1102174" />
            <int name="6" value="1402006" />
            <int name="7" value="1432016" />
            <int name="8" value="2020005" />
            <int name="9" value="2022000" />
            <int name="10" value="4004002" />
            <int name="11" value="4004003" />
            <int name="12" value="4010006" />
            <int name="13" value="4020000" />
        </imgdir>
    </imgdir>
    <imgdir name="5150002">
        <string name="episode" value="" />
        <imgdir name="map">
            <int name="0" value="106010103" />
            <int name="1" value="106010105" />
        </imgdir>
        <imgdir name="reward">
            <int name="0" value="1002075" />
            <int name="1" value="1032025" />
            <int name="2" value="1040033" />
            <int name="3" value="1052095" />
            <int name="4" value="1072009" />
            <int name="5" value="1082012" />
            <int name="6" value="1102174" />
            <int name="7" value="1332020" />
            <int name="8" value="1372001" />
            <int name="9" value="2020005" />
            <int name="10" value="2022000" />
            <int name="11" value="4004001" />
            <int name="12" value="4010002" />
            <int name="13" value="4020005" />
        </imgdir>
    </imgdir>
    <imgdir name="4230103">
        <string name="episode" value="" />
        <imgdir name="map">
            <int name="0" value="100000005" />
        </imgdir>
        <imgdir name="reward">
            <int name="0" value="1002042" />
            <int name="1" value="1012076" />
            <int name="2" value="1041029" />
            <int name="3" value="1060025" />
            <int name="4" value="1072016" />
            <int name="5" value="1082183" />
            <int name="6" value="1132000" />
            <int name="7" value="1332001" />
            <int name="8" value="1382001" />
            <int name="9" value="2020008" />
            <int name="10" value="2020010" />
        </imgdir>
    </imgdir>
    <imgdir name="4230504">
        <string name="episode" value="" />
        <imgdir name="map">
            <int name="0" value="106010110" />
        </imgdir>
        <imgdir name="reward">
            <int name="0" value="1002104" />
            <int name="1" value="1032004" />
            <int name="2" value="1032005" />
            <int name="3" value="1040037" />
            <int name="4" value="1062002" />
            <int name="5" value="1072288" />
            <int name="6" value="1082033" />
            <int name="7" value="1092005" />
            <int name="8" value="1402007" />
            <int name="9" value="1432005" />
            <int name="10" value="2020008" />
            <int name="11" value="2020010" />
            <int name="12" value="4000021" />
            <int name="13" value="4010005" />
            <int name="14" value="4020004" />
        </imgdir>
    </imgdir>
    <imgdir name="4230503">
        <string name="episode" value="" />
        <imgdir name="map">
            <int name="0" value="106010110" />
        </imgdir>
        <imgdir name="reward">
            <int name="0" value="1002616" />
            <int name="1" value="1032006" />
            <int name="2" value="1051000" />
            <int name="3" value="1061059" />
            <int name="4" value="1072028" />
            <int name="5" value="1082022" />
            <int name="6" value="1092018" />
            <int name="7" value="1132000" />
            <int name="8" value="1442003" />
            <int name="9" value="1452007" />
            <int name="10" value="2020008" />
            <int name="11" value="2020010" />
            <int name="12" value="4007011" />
            <int name="13" value="4010000" />
            <int name="14" value="4020006" />
        </imgdir>
    </imgdir>
    <imgdir name="2130103">
        <string name="episode" value="" />
        <imgdir name="map">
            <int name="0" value="106010110" />
        </imgdir>
        <imgdir name="reward">
            <int name="0" value="1002108" />
            <int name="1" value="1012076" />
            <int name="2" value="1032025" />
            <int name="3" value="1040011" />
            <int name="4" value="1052101" />
            <int name="5" value="1072024" />
            <int name="6" value="1082000" />
            <int name="7" value="1092021" />
            <int name="8" value="1462048" />
            <int name="9" value="1472015" />
            <int name="10" value="2020008" />
            <int name="11" value="2020010" />
            <int name="12" value="4010003" />
            <int name="13" value="4020003" />
            <int name="14" value="4021017" />
        </imgdir>
    </imgdir>
    <imgdir name="2300200">
        <string name="episode" value="" />
        <imgdir name="map">
            <int name="0" value="106010109" />
        </imgdir>
        <imgdir name="reward">
            <int name="0" value="1002619" />
            <int name="1" value="1040035" />
            <int name="2" value="1060015" />
            <int name="3" value="1072047" />
            <int name="4" value="1082014" />
            <int name="5" value="1482006" />
            <int name="6" value="1492006" />
            <int name="7" value="2020008" />
            <int name="8" value="2020010" />
            <int name="9" value="4004001" />
            <int name="10" value="4010004" />
            <int name="11" value="4020007" />
        </imgdir>
    </imgdir>
    <imgdir name="2300208">
        <string name="episode" value="" />
        <imgdir name="map">
            <int name="0" value="106010112" />
        </imgdir>
        <imgdir name="reward">
            <int name="0" value="1002007" />
            <int name="1" value="1002112" />
            <int name="2" value="1041045" />
            <int name="3" value="1061027" />
            <int name="4" value="1072288" />
            <int name="5" value="1322031" />
            <int name="6" value="1382001" />
            <int name="7" value="1402007" />
            <int name="8" value="2020008" />
            <int name="9" value="2020010" />
            <int name="10" value="4004003" />
            <int name="11" value="4010001" />
            <int name="12" value="4020002" />
        </imgdir>
    </imgdir>
    <imgdir name="2400306">
        <string name="episode" value="" />
        <imgdir name="map">
            <int name="0" value="106010111" />
        </imgdir>
        <imgdir name="reward">
            <int name="0" value="1002113" />
            <int name="1" value="1041063" />
            <int name="2" value="1061038" />
            <int name="3" value="1072024" />
            <int name="4" value="1082033" />
            <int name="5" value="1442003" />
            <int name="6" value="1462048" />
            <int name="7" value="1492006" />
            <int name="8" value="2020008" />
            <int name="9" value="2020010" />
            <int name="10" value="4004000" />
            <int name="11" value="4010000" />
            <int name="12" value="4020005" />
        </imgdir>
    </imgdir>
    <imgdir name="2400305">
        <string name="episode" value="" />
        <imgdir name="map">
            <int name="0" value="106010111" />
        </imgdir>
        <imgdir name="reward">
            <int name="0" value="1002105" />
            <int name="1" value="1052101" />
            <int name="2" value="1060027" />
            <int name="3" value="1072028" />
            <int name="4" value="1082014" />
            <int name="5" value="1332001" />
            <int name="6" value="1432005" />
            <int name="7" value="1452007" />
            <int name="8" value="2020008" />
            <int name="9" value="2020010" />
            <int name="10" value="4004002" />
            <int name="11" value="4010006" />
            <int name="12" value="4020001" />
        </imgdir>
    </imgdir>
    <imgdir name="4230100">
        <string name="episode" value="" />
        <imgdir name="map">
            <int name="0" value="106010113" />
        </imgdir>
        <imgdir name="reward">
            <int name="0" value="1002111" />
            <int name="1" value="1040019" />
            <int name="2" value="1072016" />
            <int name="3" value="1082000" />
            <int name="4" value="1082022" />
            <int name="5" value="1082183" />
            <int name="6" value="1322031" />
            <int name="7" value="1472015" />
            <int name="8" value="1482006" />
            <int name="9" value="2020008" />
            <int name="10" value="2020010" />
            <int name="11" value="4010001" />
            <int name="12" value="4020007" />
            <int name="13" value="4021017" />
        </imgdir>
    </imgdir>
    <imgdir name="9420005">
        <string name="episode" value="" />
        <imgdir name="map">
            <int name="0" value="100000007" />
        </imgdir>
        <imgdir name="reward" />
    </imgdir>
    <imgdir name="9400597">
        <string name="episode" value="" />
        <imgdir name="map" />
        <imgdir name="reward">
            <int name="0" value="4007034" />
            <int name="1" value="4007035" />
            <int name="2" value="4007036" />
            <int name="3" value="4007037" />
            <int name="4" value="4130100" />
            <int name="5" value="5010000" />
            <int name="6" value="5010001" />
            <int name="7" value="5010002" />
            <int name="8" value="5010003" />
            <int name="9" value="5010004" />
            <int name="10" value="5010005" />
            <int name="11" value="5010006" />
            <int name="12" value="5010007" />
            <int name="13" value="5010008" />
            <int name="14" value="5010009" />
            <int name="15" value="5010010" />
            <int name="16" value="5010011" />
            <int name="17" value="5010012" />
            <int name="18" value="5010013" />
            <int name="19" value="5010014" />
            <int name="20" value="5010015" />
            <int name="21" value="5010016" />
            <int name="22" value="5010017" />
            <int name="23" value="5010018" />
            <int name="24" value="5010019" />
            <int name="25" value="5010020" />
            <int name="26" value="5010021" />
            <int name="27" value="5010022" />
            <int name="28" value="5010023" />
            <int name="29" value="5010024" />
            <int name="30" value="5010025" />
            <int name="31" value="5010026" />
            <int name="32" value="5010027" />
            <int name="33" value="5010028" />
            <int name="34" value="5010029" />
            <int name="35" value="5010030" />
            <int name="36" value="5010031" />
            <int name="37" value="5010032" />
            <int name="38" value="5010033" />
            <int name="39" value="5010034" />
            <int name="40" value="5010035" />
            <int name="41" value="5010038" />
            <int name="42" value="5010041" />
            <int name="43" value="5010042" />
            <int name="44" value="5010043" />
            <int name="45" value="5010044" />
            <int name="46" value="5010045" />
            <int name="47" value="5010046" />
            <int name="48" value="5010048" />
            <int name="49" value="5010049" />
            <int name="50" value="5010051" />
            <int name="51" value="5010052" />
            <int name="52" value="5010053" />
            <int name="53" value="5010054" />
            <int name="54" value="5010055" />
            <int name="55" value="5010056" />
            <int name="56" value="5010057" />
            <int name="57" value="5060000" />
            <int name="58" value="5060001" />
            <int name="59" value="5076000" />
            <int name="60" value="5130000" />
            <int name="61" value="5170000" />
            <int name="62" value="5220000" />
            <int name="63" value="5220010" />
            <int name="64" value="5220020" />
            <int name="65" value="5370000" />
        </imgdir>
    </imgdir>
    <imgdir name="3300008">
        <string name="episode" value="" />
        <imgdir name="map" />
        <imgdir name="reward">
            <int name="0" value="4007034" />
            <int name="1" value="4007035" />
            <int name="2" value="4007036" />
            <int name="3" value="4007037" />
            <int name="4" value="4130100" />
            <int name="5" value="5010000" />
            <int name="6" value="5010001" />
            <int name="7" value="5010002" />
            <int name="8" value="5010003" />
            <int name="9" value="5010004" />
            <int name="10" value="5010005" />
            <int name="11" value="5010006" />
            <int name="12" value="5010007" />
            <int name="13" value="5010008" />
            <int name="14" value="5010009" />
            <int name="15" value="5010010" />
            <int name="16" value="5010011" />
            <int name="17" value="5010012" />
            <int name="18" value="5010013" />
            <int name="19" value="5010014" />
            <int name="20" value="5010015" />
            <int name="21" value="5010016" />
            <int name="22" value="5010017" />
            <int name="23" value="5010018" />
            <int name="24" value="5010019" />
            <int name="25" value="5010020" />
            <int name="26" value="5010021" />
            <int name="27" value="5010022" />
            <int name="28" value="5010023" />
            <int name="29" value="5010024" />
            <int name="30" value="5010025" />
            <int name="31" value="5010026" />
            <int name="32" value="5010027" />
            <int name="33" value="5010028" />
            <int name="34" value="5010029" />
            <int name="35" value="5010030" />
            <int name="36" value="5010031" />
            <int name="37" value="5010032" />
            <int name="38" value="5010033" />
            <int name="39" value="5010034" />
            <int name="40" value="5010035" />
            <int name="41" value="5010038" />
            <int name="42" value="5010041" />
            <int name="43" value="5010042" />
            <int name="44" value="5010043" />
            <int name="45" value="5010044" />
            <int name="46" value="5010045" />
            <int name="47" value="5010046" />
            <int name="48" value="5010048" />
            <int name="49" value="5010049" />
            <int name="50" value="5010051" />
            <int name="51" value="5010052" />
            <int name="52" value="5010053" />
            <int name="53" value="5010054" />
            <int name="54" value="5010055" />
            <int name="55" value="5010056" />
            <int name="56" value="5010057" />
            <int name="57" value="5060000" />
            <int name="58" value="5060001" />
            <int name="59" value="5076000" />
            <int name="60" value="5130000" />
            <int name="61" value="5170000" />
            <int name="62" value="5220000" />
            <int name="63" value="5220010" />
            <int name="64" value="5220020" />
            <int name="65" value="5370000" />
        </imgdir>
    </imgdir>
    <imgdir name="8211004">
        <string name="episode" value="" />
        <imgdir name="map">
            <int name="0" value="106010102" />
        </imgdir>
        <imgdir name="reward">
            <int name="0" value="1002002" />
            <int name="1" value="1002010" />
            <int name="2" value="1002044" />
            <int name="3" value="1002057" />
            <int name="4" value="1002074" />
            <int name="5" value="1002075" />
            <int name="6" value="1002124" />
            <int name="7" value="1002125" />
            <int name="8" value="1002610" />
            <int name="9" value="1002613" />
            <int name="10" value="1012076" />
            <int name="11" value="1032004" />
            <int name="12" value="1032005" />
            <int name="13" value="1032006" />
            <int name="14" value="1032025" />
            <int name="15" value="1040004" />
            <int name="16" value="1040015" />
            <int name="17" value="1040032" />
            <int name="18" value="1040033" />
            <int name="19" value="1040071" />
            <int name="20" value="1041017" />
            <int name="21" value="1041061" />
            <int name="22" value="1041064" />
            <int name="23" value="1052095" />
            <int name="24" value="1060008" />
            <int name="25" value="1060012" />
            <int name="26" value="1060022" />
            <int name="27" value="1060023" />
            <int name="28" value="1061010" />
            <int name="29" value="1061023" />
            <int name="30" value="1061057" />
            <int name="31" value="1062004" />
            <int name="32" value="1072009" />
            <int name="33" value="1072015" />
            <int name="34" value="1072044" />
            <int name="35" value="1072071" />
            <int name="36" value="1072285" />
            <int name="37" value="1082003" />
            <int name="38" value="1082012" />
            <int name="39" value="1082019" />
            <int name="40" value="1082030" />
            <int name="41" value="1082180" />
            <int name="42" value="1092005" />
            <int name="43" value="1092018" />
            <int name="44" value="1092021" />
            <int name="45" value="1102174" />
            <int name="46" value="1112407" />
            <int name="47" value="1112408" />
            <int name="48" value="1112931" />
            <int name="49" value="1132000" />
            <int name="50" value="1322008" />
            <int name="51" value="1332020" />
            <int name="52" value="1372001" />
            <int name="53" value="1402006" />
            <int name="54" value="1432016" />
            <int name="55" value="1442050" />
            <int name="56" value="1452006" />
            <int name="57" value="1462005" />
            <int name="58" value="1472013" />
            <int name="59" value="1482005" />
            <int name="60" value="1492005" />
            <int name="61" value="4000021" />
            <int name="62" value="4004000" />
            <int name="63" value="4004001" />
            <int name="64" value="4004002" />
            <int name="65" value="4004003" />
            <int name="66" value="4007011" />
            <int name="67" value="4007032" />
            <int name="68" value="4010000" />
            <int name="69" value="4010001" />
            <int name="70" value="4010002" />
            <int name="71" value="4010003" />
            <int name="72" value="4010004" />
            <int name="73" value="4010005" />
            <int name="74" value="4010006" />
            <int name="75" value="4020000" />
            <int name="76" value="4020001" />
            <int name="77" value="4020002" />
            <int name="78" value="4020003" />
            <int name="79" value="4020004" />
            <int name="80" value="4020005" />
            <int name="81" value="4020006" />
            <int name="82" value="4020007" />
            <int name="83" value="4021017" />
        </imgdir>
    </imgdir>
    <imgdir name="6130101">
        <string name="episode" value="" />
        <imgdir name="map">
            <int name="0" value="100000005" />
        </imgdir>
        <imgdir name="reward">
            <int name="0" value="1002007" />
            <int name="1" value="1002042" />
            <int name="2" value="1002104" />
            <int name="3" value="1002105" />
            <int name="4" value="1002108" />
            <int name="5" value="1002111" />
            <int name="6" value="1002112" />
            <int name="7" value="1002113" />
            <int name="8" value="1002616" />
            <int name="9" value="1002619" />
            <int name="10" value="1040011" />
            <int name="11" value="1040019" />
            <int name="12" value="1040035" />
            <int name="13" value="1040037" />
            <int name="14" value="1041029" />
            <int name="15" value="1041045" />
            <int name="16" value="1041063" />
            <int name="17" value="1051000" />
            <int name="18" value="1052101" />
            <int name="19" value="1060015" />
            <int name="20" value="1060025" />
            <int name="21" value="1060027" />
            <int name="22" value="1061027" />
            <int name="23" value="1061038" />
            <int name="24" value="1061059" />
            <int name="25" value="1062002" />
            <int name="26" value="1072016" />
            <int name="27" value="1072024" />
            <int name="28" value="1072028" />
            <int name="29" value="1072047" />
            <int name="30" value="1072288" />
            <int name="31" value="1082000" />
            <int name="32" value="1082014" />
            <int name="33" value="1082022" />
            <int name="34" value="1082033" />
            <int name="35" value="1082183" />
            <int name="36" value="1322031" />
            <int name="37" value="1332001" />
            <int name="38" value="1382001" />
            <int name="39" value="1402007" />
            <int name="40" value="1432005" />
            <int name="41" value="1442003" />
            <int name="42" value="1452007" />
            <int name="43" value="1462048" />
            <int name="44" value="1472015" />
            <int name="45" value="1482006" />
            <int name="46" value="1492006" />
            <int name="47" value="4000021" />
            <int name="48" value="4000040" />
            <int name="49" value="4004000" />
            <int name="50" value="4004001" />
            <int name="51" value="4004002" />
            <int name="52" value="4004003" />
            <int name="53" value="4007011" />
            <int name="54" value="4007032" />
            <int name="55" value="4010000" />
            <int name="56" value="4010001" />
            <int name="57" value="4010002" />
            <int name="58" value="4010003" />
            <int name="59" value="4010004" />
            <int name="60" value="4010005" />
            <int name="61" value="4010006" />
            <int name="62" value="4020000" />
            <int name="63" value="4020001" />
            <int name="64" value="4020002" />
            <int name="65" value="4020003" />
            <int name="66" value="4020004" />
            <int name="67" value="4020005" />
            <int name="68" value="4020006" />
            <int name="69" value="4020007" />
            <int name="70" value="4021017" />
        </imgdir>
    </imgdir>
</imgdir>